odoo/addons/purchase_invoice_plan_deposit/README.rst
odoo/addons/purchase_invoice_plan_deposit/__init__.py
odoo/addons/purchase_invoice_plan_deposit/__manifest__.py
odoo/addons/purchase_invoice_plan_deposit/i18n/purchase_invoice_plan_deposit.pot
odoo/addons/purchase_invoice_plan_deposit/models/__init__.py
odoo/addons/purchase_invoice_plan_deposit/models/purchase.py
odoo/addons/purchase_invoice_plan_deposit/readme/CONTRIBUTORS.rst
odoo/addons/purchase_invoice_plan_deposit/readme/DESCRIPTION.rst
odoo/addons/purchase_invoice_plan_deposit/static/description/icon.png
odoo/addons/purchase_invoice_plan_deposit/static/description/index.html
odoo12_addon_purchase_invoice_plan_deposit-12.0.1.0.1.dist-info/METADATA
odoo12_addon_purchase_invoice_plan_deposit-12.0.1.0.1.dist-info/WHEEL
odoo12_addon_purchase_invoice_plan_deposit-12.0.1.0.1.dist-info/top_level.txt
odoo12_addon_purchase_invoice_plan_deposit-12.0.1.0.1.dist-info/RECORD
