Metadata-Version: 2.1
Name: odoo12-addon-purchase-invoice-plan-deposit
Version: 12.0.1.0.1
Summary: Bridge module for purchase_invoice_plan and purchase_deposit
Home-page: https://github.com/OCA/purchase-workflow
Author: Ecosoft, Odoo Community Association (OCA)
Author-email: support@odoo-community.org
License: AGPL-3
Platform: UNKNOWN
Classifier: Programming Language :: Python
Classifier: Framework :: Odoo
Classifier: Framework :: Odoo :: 12.0
Classifier: License :: OSI Approved :: GNU Affero General Public License v3
Classifier: Development Status :: 3 - Alpha
Requires-Python: >=3.5
Requires-Dist: odoo12-addon-purchase-deposit
Requires-Dist: odoo12-addon-purchase-invoice-plan
Requires-Dist: odoo (<12.1dev,>=12.0a)
